{"1418824": {"fixture": {"id": 1418824, "date": "2025-09-19T14:00:00+00:00", "venue": {"id": null, "name": "Al Salam Stadium", "city": "al-Qāhirah (Cairo)"}, "status": {"long": "Second Half", "short": "2H", "elapsed": 63}}, "league": {"id": 233, "name": "Premier League", "country": "Egypt", "logo": "https://media.api-sports.io/football/leagues/233.png", "season": 2025}, "teams": {"home": {"id": 1046, "name": "Wadi Degla", "logo": "https://media.api-sports.io/football/teams/1046.png"}, "away": {"id": 1039, "name": "El Geish", "logo": "https://media.api-sports.io/football/teams/1039.png"}}, "goals": {"home": 0, "away": 0}, "score": {"halftime": {"home": 0, "away": 0}, "fulltime": {"home": null, "away": null}, "extratime": {"home": null, "away": null}, "penalty": {"home": null, "away": null}}}, "1469715": {"fixture": {"id": 1469715, "date": "2025-09-19T14:00:00+00:00", "venue": {"id": 1563, "name": "Stade de Kégué", "city": "Lomé"}, "status": {"long": "Second Half", "short": "2H", "elapsed": 68}}, "league": {"id": 12, "name": "CAF Champions League", "country": "World", "logo": "https://media.api-sports.io/football/leagues/12.png", "season": 2025}, "teams": {"home": {"id": 16421, "name": "Dadjè", "logo": "https://media.api-sports.io/football/teams/16421.png"}, "away": {"id": 12424, "name": "Al Ahli Tripoli", "logo": "https://media.api-sports.io/football/teams/12424.png"}}, "goals": {"home": 0, "away": 0}, "score": {"halftime": {"home": 0, "away": 0}, "fulltime": {"home": null, "away": null}, "extratime": {"home": null, "away": null}, "penalty": {"home": null, "away": null}}}, "1469716": {"fixture": {"id": 1469716, "date": "2025-09-19T15:00:00+00:00", "venue": {"id": 3712, "name": "Estádio 11 de Novembro", "city": "Luanda"}, "status": {"long": "First Half", "short": "1H", "elapsed": 26}}, "league": {"id": 12, "name": "CAF Champions League", "country": "World", "logo": "https://media.api-sports.io/football/leagues/12.png", "season": 2025}, "teams": {"home": {"id": 6383, "name": "Wiliete", "logo": "https://media.api-sports.io/football/teams/6383.png"}, "away": {"id": 5370, "name": "Young Africans", "logo": "https://media.api-sports.io/football/teams/5370.png"}}, "goals": {"home": 0, "away": 0}, "score": {"halftime": {"home": 0, "away": 0}, "fulltime": {"home": null, "away": null}, "extratime": {"home": null, "away": null}, "penalty": {"home": null, "away": null}}}, "1435934": {"fixture": {"id": 1435934, "date": "2025-09-19T15:15:00+00:00", "venue": {"id": null, "name": "Prince Mohamed bin Fahd Stadium", "city": "Khobar"}, "status": {"long": "First Half", "short": "1H", "elapsed": 13}}, "league": {"id": 307, "name": "Pro League", "country": "Saudi-Arabia", "logo": "https://media.api-sports.io/football/leagues/307.png", "season": 2025}, "teams": {"home": {"id": 2933, "name": "Al-Qadisiyah FC", "logo": "https://media.api-sports.io/football/teams/2933.png"}, "away": {"id": 2928, "name": "Al Khaleej Saihat", "logo": "https://media.api-sports.io/football/teams/2928.png"}}, "goals": {"home": 1, "away": 0}, "score": {"halftime": {"home": 1, "away": 0}, "fulltime": {"home": null, "away": null}, "extratime": {"home": null, "away": null}, "penalty": {"home": null, "away": null}}}, "1435935": {"fixture": {"id": 1435935, "date": "2025-09-19T15:35:00+00:00", "venue": {"id": 1367, "name": "Al Majma'ah Sports City Stadium", "city": "Al Majma'ah"}, "status": {"long": "Not Started", "short": "NS", "elapsed": null}}, "league": {"id": 307, "name": "Pro League", "country": "Saudi-Arabia", "logo": "https://media.api-sports.io/football/leagues/307.png", "season": 2025}, "teams": {"home": {"id": 2944, "name": "Al-Fayha", "logo": "https://media.api-sports.io/football/teams/2944.png"}, "away": {"id": 2940, "name": "Al Shabab", "logo": "https://media.api-sports.io/football/teams/2940.png"}}, "goals": {"home": null, "away": null}, "score": {"halftime": {"home": null, "away": null}, "fulltime": {"home": null, "away": null}, "extratime": {"home": null, "away": null}, "penalty": {"home": null, "away": null}}}, "1469717": {"fixture": {"id": 1469717, "date": "2025-09-19T16:00:00+00:00", "venue": {"id": 7254, "name": "Athlone Stadium", "city": "Cape Town, WC"}, "status": {"long": "Not Started", "short": "NS", "elapsed": null}}, "league": {"id": 12, "name": "CAF Champions League", "country": "World", "logo": "https://media.api-sports.io/football/leagues/12.png", "season": 2025}, "teams": {"home": {"id": 5357, "name": "African Stars", "logo": "https://media.api-sports.io/football/teams/5357.png"}, "away": {"id": 8114, "name": "Vipers", "logo": "https://media.api-sports.io/football/teams/8114.png"}}, "goals": {"home": null, "away": null}, "score": {"halftime": {"home": null, "away": null}, "fulltime": {"home": null, "away": null}, "extratime": {"home": null, "away": null}, "penalty": {"home": null, "away": null}}}, "1394482": {"fixture": {"id": 1394482, "date": "2025-09-19T17:00:00+00:00", "venue": {"id": 22441, "name": "Gürsel Aksel Stadyumu", "city": "İzmir"}, "status": {"long": "Not Started", "short": "NS", "elapsed": null}}, "league": {"id": 203, "name": "Süper Lig", "country": "Turkey", "logo": "https://media.api-sports.io/football/leagues/203.png", "season": 2025}, "teams": {"home": {"id": 994, "name": "Goztepe", "logo": "https://media.api-sports.io/football/teams/994.png"}, "away": {"id": 549, "name": "Besiktas", "logo": "https://media.api-sports.io/football/teams/549.png"}}, "goals": {"home": null, "away": null}, "score": {"halftime": {"home": null, "away": null}, "fulltime": {"home": null, "away": null}, "extratime": {"home": null, "away": null}, "penalty": {"home": null, "away": null}}}, "1418825": {"fixture": {"id": 1418825, "date": "2025-09-19T17:00:00+00:00", "venue": {"id": null, "name": "Cairo International Stadium", "city": "al-Qāhirah (Cairo)"}, "status": {"long": "Not Started", "short": "NS", "elapsed": null}}, "league": {"id": 233, "name": "Premier League", "country": "Egypt", "logo": "https://media.api-sports.io/football/leagues/233.png", "season": 2025}, "teams": {"home": {"id": 1577, "name": "Al Ahly", "logo": "https://media.api-sports.io/football/teams/1577.png"}, "away": {"id": 14651, "name": "Ceramica Cleopatra", "logo": "https://media.api-sports.io/football/teams/14651.png"}}, "goals": {"home": null, "away": null}, "score": {"halftime": {"home": null, "away": null}, "fulltime": {"home": null, "away": null}, "extratime": {"home": null, "away": null}, "penalty": {"home": null, "away": null}}}, "1418826": {"fixture": {"id": 1418826, "date": "2025-09-19T17:00:00+00:00", "venue": {"id": null, "name": "Borg El Arab Stadium", "city": "Al-Iskandarîah (Alexandria)"}, "status": {"long": "Not Started", "short": "NS", "elapsed": null}}, "league": {"id": 233, "name": "Premier League", "country": "Egypt", "logo": "https://media.api-sports.io/football/leagues/233.png", "season": 2025}, "teams": {"home": {"id": 1044, "name": "Smouha SC", "logo": "https://media.api-sports.io/football/teams/1044.png"}, "away": {"id": 1576, "name": "Haras El Hodood", "logo": "https://media.api-sports.io/football/teams/1576.png"}}, "goals": {"home": null, "away": null}, "score": {"halftime": {"home": null, "away": null}, "fulltime": {"home": null, "away": null}, "extratime": {"home": null, "away": null}, "penalty": {"home": null, "away": null}}}, "1380912": {"fixture": {"id": 1380912, "date": "2025-09-19T18:00:00+00:00", "venue": {"id": 10505, "name": "Sparta-Stadion Het Kasteel", "city": "Rotterdam"}, "status": {"long": "Not Started", "short": "NS", "elapsed": null}}, "league": {"id": 88, "name": "Eredivisie", "country": "Netherlands", "logo": "https://media.api-sports.io/football/leagues/88.png", "season": 2025}, "teams": {"home": {"id": 426, "name": "Sparta Rotterdam", "logo": "https://media.api-sports.io/football/teams/426.png"}, "away": {"id": 415, "name": "Twente", "logo": "https://media.api-sports.io/football/teams/415.png"}}, "goals": {"home": null, "away": null}, "score": {"halftime": {"home": null, "away": null}, "fulltime": {"home": null, "away": null}, "extratime": {"home": null, "away": null}, "penalty": {"home": null, "away": null}}}, "1435936": {"fixture": {"id": 1435936, "date": "2025-09-19T18:00:00+00:00", "venue": {"id": null, "name": "Al Inma Bank Stadium at King Abdullah Sport City", "city": "Jeddah"}, "status": {"long": "Not Started", "short": "NS", "elapsed": null}}, "league": {"id": 307, "name": "Pro League", "country": "Saudi-Arabia", "logo": "https://media.api-sports.io/football/leagues/307.png", "season": 2025}, "teams": {"home": {"id": 2929, "name": "Al-Ahli Jeddah", "logo": "https://media.api-sports.io/football/teams/2929.png"}, "away": {"id": 2932, "name": "Al-Hilal Saudi FC", "logo": "https://media.api-sports.io/football/teams/2932.png"}}, "goals": {"home": null, "away": null}, "score": {"halftime": {"home": null, "away": null}, "fulltime": {"home": null, "away": null}, "extratime": {"home": null, "away": null}, "penalty": {"home": null, "away": null}}}, "1388342": {"fixture": {"id": 1388342, "date": "2025-09-19T18:30:00+00:00", "venue": {"id": 20473, "name": "MHPArena", "city": "Stuttgart"}, "status": {"long": "Not Started", "short": "NS", "elapsed": null}}, "league": {"id": 78, "name": "Bundesliga", "country": "Germany", "logo": "https://media.api-sports.io/football/leagues/78.png", "season": 2025}, "teams": {"home": {"id": 172, "name": "VfB Stuttgart", "logo": "https://media.api-sports.io/football/teams/172.png"}, "away": {"id": 186, "name": "FC St. Pauli", "logo": "https://media.api-sports.io/football/teams/186.png"}}, "goals": {"home": null, "away": null}, "score": {"halftime": {"home": null, "away": null}, "fulltime": {"home": null, "away": null}, "extratime": {"home": null, "away": null}, "penalty": {"home": null, "away": null}}}, "1377899": {"fixture": {"id": 1377899, "date": "2025-09-19T18:45:00+00:00", "venue": {"id": 0, "name": "Stadio Ettore Giardiniero - Via del Mare", "city": "Lecce"}, "status": {"long": "Not Started", "short": "NS", "elapsed": null}}, "league": {"id": 135, "name": "Serie A", "country": "Italy", "logo": "https://media.api-sports.io/football/leagues/135.png", "season": 2025}, "teams": {"home": {"id": 867, "name": "Lecce", "logo": "https://media.api-sports.io/football/teams/867.png"}, "away": {"id": 490, "name": "Cagliari", "logo": "https://media.api-sports.io/football/teams/490.png"}}, "goals": {"home": null, "away": null}, "score": {"halftime": {"home": null, "away": null}, "fulltime": {"home": null, "away": null}, "extratime": {"home": null, "away": null}, "penalty": {"home": null, "away": null}}}, "1387738": {"fixture": {"id": 1387738, "date": "2025-09-19T18:45:00+00:00", "venue": {"id": 666, "name": "Groupama Stadium", "city": "Décines-Charpieu"}, "status": {"long": "Not Started", "short": "NS", "elapsed": null}}, "league": {"id": 61, "name": "Ligue 1", "country": "France", "logo": "https://media.api-sports.io/football/leagues/61.png", "season": 2025}, "teams": {"home": {"id": 80, "name": "Lyon", "logo": "https://media.api-sports.io/football/teams/80.png"}, "away": {"id": 77, "name": "Angers", "logo": "https://media.api-sports.io/football/teams/77.png"}}, "goals": {"home": null, "away": null}, "score": {"halftime": {"home": null, "away": null}, "fulltime": {"home": null, "away": null}, "extratime": {"home": null, "away": null}, "penalty": {"home": null, "away": null}}}, "1390861": {"fixture": {"id": 1390861, "date": "2025-09-19T19:00:00+00:00", "venue": {"id": null, "name": "Estadio La Cartuja de Sevilla", "city": "Sevilla"}, "status": {"long": "Not Started", "short": "NS", "elapsed": null}}, "league": {"id": 140, "name": "La Liga", "country": "Spain", "logo": "https://media.api-sports.io/football/leagues/140.png", "season": 2025}, "teams": {"home": {"id": 543, "name": "Real Betis", "logo": "https://media.api-sports.io/football/teams/543.png"}, "away": {"id": 548, "name": "Real Sociedad", "logo": "https://media.api-sports.io/football/teams/548.png"}}, "goals": {"home": null, "away": null}, "score": {"halftime": {"home": null, "away": null}, "fulltime": {"home": null, "away": null}, "extratime": {"home": null, "away": null}, "penalty": {"home": null, "away": null}}}, "1466644": {"fixture": {"id": 1466644, "date": "2025-09-19T19:00:00+00:00", "venue": {"id": null, "name": null, "city": null}, "status": {"long": "Not Started", "short": "NS", "elapsed": null}}, "league": {"id": 200, "name": "Botola Pro", "country": "Morocco", "logo": "https://media.api-sports.io/football/leagues/200.png", "season": 2025}, "teams": {"home": {"id": 25058, "name": "Yacoub El Mansour", "logo": "https://media.api-sports.io/football/teams/25058.png"}, "away": {"id": 968, "name": "Wydad AC", "logo": "https://media.api-sports.io/football/teams/968.png"}}, "goals": {"home": null, "away": null}, "score": {"halftime": {"home": null, "away": null}, "fulltime": {"home": null, "away": null}, "extratime": {"home": null, "away": null}, "penalty": {"home": null, "away": null}}}, "1396286": {"fixture": {"id": 1396286, "date": "2025-09-19T19:15:00+00:00", "venue": {"id": 1288, "name": "Estádio do Rio Ave Futebol Clube", "city": "Vila do Conde"}, "status": {"long": "Not Started", "short": "NS", "elapsed": null}}, "league": {"id": 94, "name": "Primeira Liga", "country": "Portugal", "logo": "https://media.api-sports.io/football/leagues/94.png", "season": 2025}, "teams": {"home": {"id": 226, "name": "Rio Ave", "logo": "https://media.api-sports.io/football/teams/226.png"}, "away": {"id": 212, "name": "FC Porto", "logo": "https://media.api-sports.io/football/teams/212.png"}}, "goals": {"home": null, "away": null}, "score": {"halftime": {"home": null, "away": null}, "fulltime": {"home": null, "away": null}, "extratime": {"home": null, "away": null}, "penalty": {"home": null, "away": null}}}, "1374191": {"fixture": {"id": 1374191, "date": "2025-09-19T20:00:00+00:00", "venue": {"id": 66, "name": "Estadio Guillermo Laza", "city": "Capital Federal, Ciudad de Buenos Aires"}, "status": {"long": "Not Started", "short": "NS", "elapsed": null}}, "league": {"id": 128, "name": "Liga Profesional Argentina", "country": "Argentina", "logo": "https://media.api-sports.io/football/leagues/128.png", "season": 2025}, "teams": {"home": {"id": 476, "name": "Deportivo Riestra", "logo": "https://media.api-sports.io/football/teams/476.png"}, "away": {"id": 434, "name": "Gimnasia L.P.", "logo": "https://media.api-sports.io/football/teams/434.png"}}, "goals": {"home": null, "away": null}, "score": {"halftime": {"home": null, "away": null}, "fulltime": {"home": null, "away": null}, "extratime": {"home": null, "away": null}, "penalty": {"home": null, "away": null}}}, "1374189": {"fixture": {"id": 1374189, "date": "2025-09-19T22:00:00+00:00", "venue": {"id": 82, "name": "Estadio Tomás Adolfo Ducó", "city": "Capital Federal, Ciudad de Buenos Aires"}, "status": {"long": "Not Started", "short": "NS", "elapsed": null}}, "league": {"id": 128, "name": "Liga Profesional Argentina", "country": "Argentina", "logo": "https://media.api-sports.io/football/leagues/128.png", "season": 2025}, "teams": {"home": {"id": 445, "name": "Huracan", "logo": "https://media.api-sports.io/football/teams/445.png"}, "away": {"id": 436, "name": "Racing Club", "logo": "https://media.api-sports.io/football/teams/436.png"}}, "goals": {"home": null, "away": null}, "score": {"halftime": {"home": null, "away": null}, "fulltime": {"home": null, "away": null}, "extratime": {"home": null, "away": null}, "penalty": {"home": null, "away": null}}}, "1374193": {"fixture": {"id": 1374193, "date": "2025-09-19T22:15:00+00:00", "venue": {"id": 104, "name": "Estadio Ingeniero Hilario Sánchez", "city": "San Juan, Provincia de San Juan"}, "status": {"long": "Not Started", "short": "NS", "elapsed": null}}, "league": {"id": 128, "name": "Liga Profesional Argentina", "country": "Argentina", "logo": "https://media.api-sports.io/football/leagues/128.png", "season": 2025}, "teams": {"home": {"id": 461, "name": "San Martin S.J.", "logo": "https://media.api-sports.io/football/teams/461.png"}, "away": {"id": 438, "name": "Velez Sarsfield", "logo": "https://media.api-sports.io/football/teams/438.png"}}, "goals": {"home": null, "away": null}, "score": {"halftime": {"home": null, "away": null}, "fulltime": {"home": null, "away": null}, "extratime": {"home": null, "away": null}, "penalty": {"home": null, "away": null}}}}