{"1351167": {"fixture": {"id": 1351167, "date": "2025-10-09T00:00:00+00:00", "referee": null, "venue": {"id": 5676, "name": "Estádio José Maria de Campos Maia", "city": "Mirassol"}, "status": {"long": "Not Started", "short": "NS", "elapsed": null}}, "league": {"id": 71, "name": "Serie A", "country": "Brazil", "logo": "https://media.api-sports.io/football/leagues/71.png", "season": 2025}, "teams": {"home": {"id": 7848, "name": "Mirassol", "logo": "https://media.api-sports.io/football/teams/7848.png"}, "away": {"id": 124, "name": "Fluminense", "logo": "https://media.api-sports.io/football/teams/124.png"}}, "goals": {"home": null, "away": null}, "score": {"halftime": {"home": null, "away": null}, "fulltime": {"home": null, "away": null}, "extratime": {"home": null, "away": null}, "penalty": {"home": null, "away": null}}}, "1326472": {"fixture": {"id": 1326472, "date": "2025-10-09T02:30:00+00:00", "referee": null, "venue": {"id": null, "name": "BMO Stadium", "city": null}, "status": {"long": "Not Started", "short": "NS", "elapsed": null}}, "league": {"id": 253, "name": "Major League Soccer", "country": "USA", "logo": "https://media.api-sports.io/football/leagues/253.png", "season": 2025}, "teams": {"home": {"id": 1616, "name": "Los Angeles FC", "logo": "https://media.api-sports.io/football/teams/1616.png"}, "away": {"id": 1601, "name": "Toronto FC", "logo": "https://media.api-sports.io/football/teams/1601.png"}}, "goals": {"home": null, "away": null}, "score": {"halftime": {"home": null, "away": null}, "fulltime": {"home": null, "away": null}, "extratime": {"home": null, "away": null}, "penalty": {"home": null, "away": null}}}, "1478236": {"fixture": {"id": 1478236, "date": "2025-10-09T12:00:00+00:00", "referee": null, "venue": {"id": null, "name": null, "city": null}, "status": {"long": "Not Started", "short": "NS", "elapsed": null}}, "league": {"id": 1088, "name": "Pernambucano - U20", "country": "Brazil", "logo": "https://media.api-sports.io/football/leagues/1088.png", "season": 2025}, "teams": {"home": {"id": 12971, "name": "Sport Recife U20", "logo": "https://media.api-sports.io/football/teams/12971.png"}, "away": {"id": 13053, "name": "Santa Cruz U20", "logo": "https://media.api-sports.io/football/teams/13053.png"}}, "goals": {"home": null, "away": null}, "score": {"halftime": {"home": null, "away": null}, "fulltime": {"home": null, "away": null}, "extratime": {"home": null, "away": null}, "penalty": {"home": null, "away": null}}}, "1350023": {"fixture": {"id": 1350023, "date": "2025-10-09T16:30:00+00:00", "referee": null, "venue": {"id": null, "name": "Dens Park", "city": "Dundee"}, "status": {"long": "Not Started", "short": "NS", "elapsed": null}}, "league": {"id": 850, "name": "UEFA U21 Championship - Qualification", "country": "World", "logo": "https://media.api-sports.io/football/leagues/850.png", "season": 2027}, "teams": {"home": {"id": 8221, "name": "Scotland U21", "logo": "https://media.api-sports.io/football/teams/8221.png"}, "away": {"id": 8197, "name": "Gibraltar U21", "logo": "https://media.api-sports.io/football/teams/8197.png"}}, "goals": {"home": null, "away": null}, "score": {"halftime": {"home": null, "away": null}, "fulltime": {"home": null, "away": null}, "extratime": {"home": null, "away": null}, "penalty": {"home": null, "away": null}}}, "1350021": {"fixture": {"id": 1350021, "date": "2025-10-09T17:30:00+00:00", "referee": null, "venue": {"id": null, "name": null, "city": null}, "status": {"long": "Not Started", "short": "NS", "elapsed": null}}, "league": {"id": 850, "name": "UEFA U21 Championship - Qualification", "country": "World", "logo": "https://media.api-sports.io/football/leagues/850.png", "season": 2027}, "teams": {"home": {"id": 8178, "name": "Andorra U21", "logo": "https://media.api-sports.io/football/teams/8178.png"}, "away": {"id": 8202, "name": "Kazakhstan U21", "logo": "https://media.api-sports.io/football/teams/8202.png"}}, "goals": {"home": null, "away": null}, "score": {"halftime": {"home": null, "away": null}, "fulltime": {"home": null, "away": null}, "extratime": {"home": null, "away": null}, "penalty": {"home": null, "away": null}}}, "1337510": {"fixture": {"id": 1337510, "date": "2025-10-09T18:00:00+00:00", "referee": null, "venue": {"id": 1326, "name": "Arena Naţională", "city": "Bucureşti"}, "status": {"long": "Not Started", "short": "NS", "elapsed": null}}, "league": {"id": 10, "name": "Friendlies", "country": "World", "logo": "https://media.api-sports.io/football/leagues/10.png", "season": 2025}, "teams": {"home": {"id": 774, "name": "Romania", "logo": "https://media.api-sports.io/football/teams/774.png"}, "away": {"id": 1114, "name": "Moldova", "logo": "https://media.api-sports.io/football/teams/1114.png"}}, "goals": {"home": null, "away": null}, "score": {"halftime": {"home": null, "away": null}, "fulltime": {"home": null, "away": null}, "extratime": {"home": null, "away": null}, "penalty": {"home": null, "away": null}}}, "1478232": {"fixture": {"id": 1478232, "date": "2025-10-09T18:00:00+00:00", "referee": null, "venue": {"id": null, "name": null, "city": null}, "status": {"long": "Not Started", "short": "NS", "elapsed": null}}, "league": {"id": 1088, "name": "Pernambucano - U20", "country": "Brazil", "logo": "https://media.api-sports.io/football/leagues/1088.png", "season": 2025}, "teams": {"home": {"id": 23494, "name": "Ibis Sport Club U20", "logo": "https://media.api-sports.io/football/teams/23494.png"}, "away": {"id": 26779, "name": "Guarany U20", "logo": "https://media.api-sports.io/football/teams/26779.png"}}, "goals": {"home": null, "away": null}, "score": {"halftime": {"home": null, "away": null}, "fulltime": {"home": null, "away": null}, "extratime": {"home": null, "away": null}, "penalty": {"home": null, "away": null}}}, "1478233": {"fixture": {"id": 1478233, "date": "2025-10-09T18:00:00+00:00", "referee": null, "venue": {"id": null, "name": null, "city": null}, "status": {"long": "Not Started", "short": "NS", "elapsed": null}}, "league": {"id": 1088, "name": "Pernambucano - U20", "country": "Brazil", "logo": "https://media.api-sports.io/football/leagues/1088.png", "season": 2025}, "teams": {"home": {"id": 23495, "name": "Ipojuca U20", "logo": "https://media.api-sports.io/football/teams/23495.png"}, "away": {"id": 23498, "name": "Serrano PE U20", "logo": "https://media.api-sports.io/football/teams/23498.png"}}, "goals": {"home": null, "away": null}, "score": {"halftime": {"home": null, "away": null}, "fulltime": {"home": null, "away": null}, "extratime": {"home": null, "away": null}, "penalty": {"home": null, "away": null}}}, "1478234": {"fixture": {"id": 1478234, "date": "2025-10-09T18:00:00+00:00", "referee": null, "venue": {"id": null, "name": null, "city": null}, "status": {"long": "Not Started", "short": "NS", "elapsed": null}}, "league": {"id": 1088, "name": "Pernambucano - U20", "country": "Brazil", "logo": "https://media.api-sports.io/football/leagues/1088.png", "season": 2025}, "teams": {"home": {"id": 23496, "name": "Jaguar U20", "logo": "https://media.api-sports.io/football/teams/23496.png"}, "away": {"id": 26778, "name": "Atletico PE U20", "logo": "https://media.api-sports.io/football/teams/26778.png"}}, "goals": {"home": null, "away": null}, "score": {"halftime": {"home": null, "away": null}, "fulltime": {"home": null, "away": null}, "extratime": {"home": null, "away": null}, "penalty": {"home": null, "away": null}}}, "1478235": {"fixture": {"id": 1478235, "date": "2025-10-09T18:00:00+00:00", "referee": null, "venue": {"id": null, "name": null, "city": null}, "status": {"long": "Not Started", "short": "NS", "elapsed": null}}, "league": {"id": 1088, "name": "Pernambucano - U20", "country": "Brazil", "logo": "https://media.api-sports.io/football/leagues/1088.png", "season": 2025}, "teams": {"home": {"id": 13029, "name": "Nautico U20", "logo": "https://media.api-sports.io/football/teams/13029.png"}, "away": {"id": 13050, "name": "Retrô U20", "logo": "https://media.api-sports.io/football/teams/13050.png"}}, "goals": {"home": null, "away": null}, "score": {"halftime": {"home": null, "away": null}, "fulltime": {"home": null, "away": null}, "extratime": {"home": null, "away": null}, "penalty": {"home": null, "away": null}}}, "1350022": {"fixture": {"id": 1350022, "date": "2025-10-09T18:45:00+00:00", "referee": null, "venue": {"id": 18636, "name": "BetMcLean Oval", "city": "Belfast"}, "status": {"long": "Not Started", "short": "NS", "elapsed": null}}, "league": {"id": 850, "name": "UEFA U21 Championship - Qualification", "country": "World", "logo": "https://media.api-sports.io/football/leagues/850.png", "season": 2027}, "teams": {"home": {"id": 8213, "name": "Northern Ireland U21", "logo": "https://media.api-sports.io/football/teams/8213.png"}, "away": {"id": 8208, "name": "Malta U21", "logo": "https://media.api-sports.io/football/teams/8208.png"}}, "goals": {"home": null, "away": null}, "score": {"halftime": {"home": null, "away": null}, "fulltime": {"home": null, "away": null}, "extratime": {"home": null, "away": null}, "penalty": {"home": null, "away": null}}}, "1352905": {"fixture": {"id": 1352905, "date": "2025-10-09T18:45:00+00:00", "referee": null, "venue": {"id": 489, "name": "Wembley Stadium", "city": "London"}, "status": {"long": "Not Started", "short": "NS", "elapsed": null}}, "league": {"id": 10, "name": "Friendlies", "country": "World", "logo": "https://media.api-sports.io/football/leagues/10.png", "season": 2025}, "teams": {"home": {"id": 10, "name": "England", "logo": "https://media.api-sports.io/football/teams/10.png"}, "away": {"id": 767, "name": "Wales", "logo": "https://media.api-sports.io/football/teams/767.png"}}, "goals": {"home": null, "away": null}, "score": {"halftime": {"home": null, "away": null}, "fulltime": {"home": null, "away": null}, "extratime": {"home": null, "away": null}, "penalty": {"home": null, "away": null}}}, "1436809": {"fixture": {"id": 1436809, "date": "2025-10-09T18:45:00+00:00", "referee": null, "venue": {"id": 20760, "name": "Stadion Śląski", "city": "Chorzów"}, "status": {"long": "Not Started", "short": "NS", "elapsed": null}}, "league": {"id": 10, "name": "Friendlies", "country": "World", "logo": "https://media.api-sports.io/football/leagues/10.png", "season": 2025}, "teams": {"home": {"id": 24, "name": "Poland", "logo": "https://media.api-sports.io/football/teams/24.png"}, "away": {"id": 4673, "name": "New Zealand", "logo": "https://media.api-sports.io/football/teams/4673.png"}}, "goals": {"home": null, "away": null}, "score": {"halftime": {"home": null, "away": null}, "fulltime": {"home": null, "away": null}, "extratime": {"home": null, "away": null}, "penalty": {"home": null, "away": null}}}, "1472255": {"fixture": {"id": 1472255, "date": "2025-10-09T19:00:00+00:00", "referee": null, "venue": {"id": 1103, "name": "Stade Prince Moulay Abdallah", "city": "Rabat"}, "status": {"long": "Not Started", "short": "NS", "elapsed": null}}, "league": {"id": 10, "name": "Friendlies", "country": "World", "logo": "https://media.api-sports.io/football/leagues/10.png", "season": 2025}, "teams": {"home": {"id": 31, "name": "Morocco", "logo": "https://media.api-sports.io/football/teams/31.png"}, "away": {"id": 1547, "name": "Bahrain", "logo": "https://media.api-sports.io/football/teams/1547.png"}}, "goals": {"home": null, "away": null}, "score": {"halftime": {"home": null, "away": null}, "fulltime": {"home": null, "away": null}, "extratime": {"home": null, "away": null}, "penalty": {"home": null, "away": null}}}, "1480426": {"fixture": {"id": 1480426, "date": "2025-10-09T19:30:00+00:00", "referee": null, "venue": {"id": null, "name": "Estadio El Teniente", "city": "Rancagua"}, "status": {"long": "Not Started", "short": "NS", "elapsed": null}}, "league": {"id": 490, "name": "World Cup - U20", "country": "World", "logo": "https://media.api-sports.io/football/leagues/490.png", "season": 2025}, "teams": {"home": {"id": 10306, "name": "United States U20", "logo": "https://media.api-sports.io/football/teams/10306.png"}, "away": {"id": 10289, "name": "Italy U20", "logo": "https://media.api-sports.io/football/teams/10289.png"}}, "goals": {"home": null, "away": null}, "score": {"halftime": {"home": null, "away": null}, "fulltime": {"home": null, "away": null}, "extratime": {"home": null, "away": null}, "penalty": {"home": null, "away": null}}}, "1480427": {"fixture": {"id": 1480427, "date": "2025-10-09T23:00:00+00:00", "referee": null, "venue": {"id": null, "name": "Estadio El Teniente", "city": "Rancagua"}, "status": {"long": "Not Started", "short": "NS", "elapsed": null}}, "league": {"id": 490, "name": "World Cup - U20", "country": "World", "logo": "https://media.api-sports.io/football/leagues/490.png", "season": 2025}, "teams": {"home": {"id": 11039, "name": "Morocco U20", "logo": "https://media.api-sports.io/football/teams/11039.png"}, "away": {"id": 10291, "name": "Korea Republic U20", "logo": "https://media.api-sports.io/football/teams/10291.png"}}, "goals": {"home": null, "away": null}, "score": {"halftime": {"home": null, "away": null}, "fulltime": {"home": null, "away": null}, "extratime": {"home": null, "away": null}, "penalty": {"home": null, "away": null}}}}