{"1501849": {"fixture": {"id": 1501849, "date": "2026-01-04T00:00:00+00:00", "referee": null, "venue": {"id": null, "name": null, "city": null}, "status": {"long": "Match Finished", "short": "FT", "elapsed": 90}}, "league": {"id": 667, "name": "Friendlies Clubs", "country": "World", "logo": "https://media.api-sports.io/football/leagues/667.png", "season": 2026}, "teams": {"home": {"id": 2307, "name": "Leones Negros UDG", "logo": "https://media.api-sports.io/football/teams/2307.png"}, "away": {"id": 2282, "name": "Monterrey", "logo": "https://media.api-sports.io/football/teams/2282.png"}}, "goals": {"home": 0, "away": 3}, "score": {"halftime": {"home": 0, "away": 2}, "fulltime": {"home": 0, "away": 3}, "extratime": {"home": null, "away": null}, "penalty": {"home": null, "away": null}}}, "1501850": {"fixture": {"id": 1501850, "date": "2026-01-04T02:45:00+00:00", "referee": null, "venue": {"id": null, "name": null, "city": null}, "status": {"long": "Match Finished", "short": "FT", "elapsed": 90}}, "league": {"id": 667, "name": "Friendlies Clubs", "country": "World", "logo": "https://media.api-sports.io/football/leagues/667.png", "season": 2026}, "teams": {"home": {"id": 2283, "name": "Atlas", "logo": "https://media.api-sports.io/football/teams/2283.png"}, "away": {"id": 2278, "name": "Guadalajara Chivas", "logo": "https://media.api-sports.io/football/teams/2278.png"}}, "goals": {"home": 0, "away": 0}, "score": {"halftime": {"home": 0, "away": 0}, "fulltime": {"home": 0, "away": 0}, "extratime": {"home": null, "away": null}, "penalty": {"home": null, "away": null}}}, "1378041": {"fixture": {"id": 1378041, "date": "2026-01-04T11:30:00+00:00", "referee": "Davide Massa, Italy", "venue": {"id": null, "name": "Stadio Olimpico", "city": "Rome"}, "status": {"long": "Match Finished", "short": "FT", "elapsed": 90}}, "league": {"id": 135, "name": "Serie A", "country": "Italy", "logo": "https://media.api-sports.io/football/leagues/135.png", "season": 2025}, "teams": {"home": {"id": 487, "name": "Lazio", "logo": "https://media.api-sports.io/football/teams/487.png"}, "away": {"id": 492, "name": "Napoli", "logo": "https://media.api-sports.io/football/teams/492.png"}}, "goals": {"home": 0, "away": 2}, "score": {"halftime": {"home": 0, "away": 2}, "fulltime": {"home": 0, "away": 2}, "extratime": {"home": null, "away": null}, "penalty": {"home": null, "away": null}}}, "1379164": {"fixture": {"id": 1379164, "date": "2026-01-04T12:30:00+00:00", "referee": "Jarred Gillett, Australia", "venue": {"id": 546, "name": "Elland Road", "city": "Leeds"}, "status": {"long": "Match Finished", "short": "FT", "elapsed": 90}}, "league": {"id": 39, "name": "Premier League", "country": "England", "logo": "https://media.api-sports.io/football/leagues/39.png", "season": 2025}, "teams": {"home": {"id": 63, "name": "Leeds", "logo": "https://media.api-sports.io/football/teams/63.png"}, "away": {"id": 33, "name": "Manchester United", "logo": "https://media.api-sports.io/football/teams/33.png"}}, "goals": {"home": 1, "away": 1}, "score": {"halftime": {"home": 0, "away": 0}, "fulltime": {"home": 1, "away": 1}, "extratime": {"home": null, "away": null}, "penalty": {"home": null, "away": null}}}, "1502451": {"fixture": {"id": 1502451, "date": "2026-01-04T12:30:00+00:00", "referee": null, "venue": {"id": null, "name": null, "city": null}, "status": {"long": "Match Finished", "short": "FT", "elapsed": 90}}, "league": {"id": 667, "name": "Friendlies Clubs", "country": "World", "logo": "https://media.api-sports.io/football/leagues/667.png", "season": 2026}, "teams": {"home": {"id": 985, "name": "Stade Gabesien", "logo": "https://media.api-sports.io/football/teams/985.png"}, "away": {"id": 10616, "name": "Kerkennah", "logo": "https://media.api-sports.io/football/teams/10616.png"}}, "goals": {"home": 0, "away": 0}, "score": {"halftime": {"home": null, "away": null}, "fulltime": {"home": 0, "away": 0}, "extratime": {"home": null, "away": null}, "penalty": {"home": null, "away": null}}}, "1501851": {"fixture": {"id": 1501851, "date": "2026-01-04T12:45:00+00:00", "referee": null, "venue": {"id": null, "name": null, "city": null}, "status": {"long": "Match Finished", "short": "FT", "elapsed": 90}}, "league": {"id": 667, "name": "Friendlies Clubs", "country": "World", "logo": "https://media.api-sports.io/football/leagues/667.png", "season": 2026}, "teams": {"home": {"id": 25615, "name": "KKP", "logo": "https://media.api-sports.io/football/teams/25615.png"}, "away": {"id": 25612, "name": "JPJ", "logo": "https://media.api-sports.io/football/teams/25612.png"}}, "goals": {"home": 1, "away": 0}, "score": {"halftime": {"home": 0, "away": 0}, "fulltime": {"home": 1, "away": 0}, "extratime": {"home": null, "away": null}, "penalty": {"home": null, "away": null}}}, "1390998": {"fixture": {"id": 1390998, "date": "2026-01-04T13:00:00+00:00", "referee": "Iosu Galech Apezteguia, Spain", "venue": {"id": 1494, "name": "Estadio Ramón Sánchez Pizjuán", "city": "Sevilla"}, "status": {"long": "Match Finished", "short": "FT", "elapsed": 90}}, "league": {"id": 140, "name": "La Liga", "country": "Spain", "logo": "https://media.api-sports.io/football/leagues/140.png", "season": 2025}, "teams": {"home": {"id": 536, "name": "Sevilla", "logo": "https://media.api-sports.io/football/teams/536.png"}, "away": {"id": 539, "name": "Levante", "logo": "https://media.api-sports.io/football/teams/539.png"}}, "goals": {"home": 0, "away": 3}, "score": {"halftime": {"home": 0, "away": 1}, "fulltime": {"home": 0, "away": 3}, "extratime": {"home": null, "away": null}, "penalty": {"home": null, "away": null}}}, "1501852": {"fixture": {"id": 1501852, "date": "2026-01-04T13:00:00+00:00", "referee": null, "venue": {"id": null, "name": null, "city": null}, "status": {"long": "Match Cancelled", "short": "CANC", "elapsed": null}}, "league": {"id": 667, "name": "Friendlies Clubs", "country": "World", "logo": "https://media.api-sports.io/football/leagues/667.png", "season": 2026}, "teams": {"home": {"id": 988, "name": "Club Africain", "logo": "https://media.api-sports.io/football/teams/988.png"}, "away": {"id": 1191, "name": "CS Hammam-Lif", "logo": "https://media.api-sports.io/football/teams/1191.png"}}, "goals": {"home": null, "away": null}, "score": {"halftime": {"home": null, "away": null}, "fulltime": {"home": null, "away": null}, "extratime": {"home": null, "away": null}, "penalty": {"home": null, "away": null}}}, "1502296": {"fixture": {"id": 1502296, "date": "2026-01-04T13:30:00+00:00", "referee": null, "venue": {"id": null, "name": null, "city": null}, "status": {"long": "Match Cancelled", "short": "CANC", "elapsed": null}}, "league": {"id": 667, "name": "Friendlies Clubs", "country": "World", "logo": "https://media.api-sports.io/football/leagues/667.png", "season": 2026}, "teams": {"home": {"id": 785, "name": "Karlsruher SC", "logo": "https://media.api-sports.io/football/teams/785.png"}, "away": {"id": 1012, "name": "FC Thun", "logo": "https://media.api-sports.io/football/teams/1012.png"}}, "goals": {"home": null, "away": null}, "score": {"halftime": {"home": null, "away": null}, "fulltime": {"home": null, "away": null}, "extratime": {"home": null, "away": null}, "penalty": {"home": null, "away": null}}}, "1378037": {"fixture": {"id": 1378037, "date": "2026-01-04T14:00:00+00:00", "referee": "Federico La Penna, Italy", "venue": {"id": null, "name": "Stadio Artemio Franchi", "city": "Florence"}, "status": {"long": "Match Finished", "short": "FT", "elapsed": 90}}, "league": {"id": 135, "name": "Serie A", "country": "Italy", "logo": "https://media.api-sports.io/football/leagues/135.png", "season": 2025}, "teams": {"home": {"id": 502, "name": "Fiorentina", "logo": "https://media.api-sports.io/football/teams/502.png"}, "away": {"id": 520, "name": "Cremonese", "logo": "https://media.api-sports.io/football/teams/520.png"}}, "goals": {"home": 1, "away": 0}, "score": {"halftime": {"home": 0, "away": 0}, "fulltime": {"home": 1, "away": 0}, "extratime": {"home": null, "away": null}, "penalty": {"home": null, "away": null}}}, "1387846": {"fixture": {"id": 1387846, "date": "2026-01-04T14:00:00+00:00", "referee": "Marc Bollengier, France", "venue": {"id": 667, "name": "Orange Vélodrome", "city": "Marseille"}, "status": {"long": "Match Finished", "short": "FT", "elapsed": 90}}, "league": {"id": 61, "name": "Ligue 1", "country": "France", "logo": "https://media.api-sports.io/football/leagues/61.png", "season": 2025}, "teams": {"home": {"id": 81, "name": "Marseille", "logo": "https://media.api-sports.io/football/teams/81.png"}, "away": {"id": 83, "name": "Nantes", "logo": "https://media.api-sports.io/football/teams/83.png"}}, "goals": {"home": 0, "away": 2}, "score": {"halftime": {"home": 0, "away": 1}, "fulltime": {"home": 0, "away": 2}, "extratime": {"home": null, "away": null}, "penalty": {"home": null, "away": null}}}, "1501853": {"fixture": {"id": 1501853, "date": "2026-01-04T14:30:00+00:00", "referee": null, "venue": {"id": null, "name": null, "city": null}, "status": {"long": "Match Finished", "short": "FT", "elapsed": 90}}, "league": {"id": 667, "name": "Friendlies Clubs", "country": "World", "logo": "https://media.api-sports.io/football/leagues/667.png", "season": 2026}, "teams": {"home": {"id": 186, "name": "FC St. Pauli", "logo": "https://media.api-sports.io/football/teams/186.png"}, "away": {"id": 162, "name": "Werder Bremen", "logo": "https://media.api-sports.io/football/teams/162.png"}}, "goals": {"home": 0, "away": 0}, "score": {"halftime": {"home": 0, "away": 0}, "fulltime": {"home": 0, "away": 0}, "extratime": {"home": null, "away": null}, "penalty": {"home": null, "away": null}}}, "1379162": {"fixture": {"id": 1379162, "date": "2026-01-04T15:00:00+00:00", "referee": "Anthony Taylor, England", "venue": {"id": 22033, "name": "Hill Dickinson Stadium", "city": "Liverpool"}, "status": {"long": "Match Finished", "short": "FT", "elapsed": 90}}, "league": {"id": 39, "name": "Premier League", "country": "England", "logo": "https://media.api-sports.io/football/leagues/39.png", "season": 2025}, "teams": {"home": {"id": 45, "name": "Everton", "logo": "https://media.api-sports.io/football/teams/45.png"}, "away": {"id": 55, "name": "Brentford", "logo": "https://media.api-sports.io/football/teams/55.png"}}, "goals": {"home": 2, "away": 4}, "score": {"halftime": {"home": 0, "away": 1}, "fulltime": {"home": 2, "away": 4}, "extratime": {"home": null, "away": null}, "penalty": {"home": null, "away": null}}}, "1379166": {"fixture": {"id": 1379166, "date": "2026-01-04T15:00:00+00:00", "referee": "John Brooks, England", "venue": {"id": 562, "name": "St. James' Park", "city": "Newcastle"}, "status": {"long": "Match Finished", "short": "FT", "elapsed": 90}}, "league": {"id": 39, "name": "Premier League", "country": "England", "logo": "https://media.api-sports.io/football/leagues/39.png", "season": 2025}, "teams": {"home": {"id": 34, "name": "Newcastle", "logo": "https://media.api-sports.io/football/teams/34.png"}, "away": {"id": 52, "name": "Crystal Palace", "logo": "https://media.api-sports.io/football/teams/52.png"}}, "goals": {"home": 2, "away": 0}, "score": {"halftime": {"home": 0, "away": 0}, "fulltime": {"home": 2, "away": 0}, "extratime": {"home": null, "away": null}, "penalty": {"home": null, "away": null}}}, "1379167": {"fixture": {"id": 1379167, "date": "2026-01-04T15:00:00+00:00", "referee": "Stuart Attwell, England", "venue": {"id": 593, "name": "Tottenham Hotspur Stadium", "city": "London"}, "status": {"long": "Match Finished", "short": "FT", "elapsed": 90}}, "league": {"id": 39, "name": "Premier League", "country": "England", "logo": "https://media.api-sports.io/football/leagues/39.png", "season": 2025}, "teams": {"home": {"id": 47, "name": "Tottenham", "logo": "https://media.api-sports.io/football/teams/47.png"}, "away": {"id": 746, "name": "Sunderland", "logo": "https://media.api-sports.io/football/teams/746.png"}}, "goals": {"home": 1, "away": 1}, "score": {"halftime": {"home": 1, "away": 0}, "fulltime": {"home": 1, "away": 1}, "extratime": {"home": null, "away": null}, "penalty": {"home": null, "away": null}}}, "1436024": {"fixture": {"id": 1436024, "date": "2026-01-04T15:05:00+00:00", "referee": "Irfan Peljto, Bosnia & Herzegovina", "venue": {"id": null, "name": "Ar-Rass Stadium", "city": "Ar Rass"}, "status": {"long": "Match Finished", "short": "FT", "elapsed": 90}}, "league": {"id": 307, "name": "Pro League", "country": "Saudi-Arabia", "logo": "https://media.api-sports.io/football/leagues/307.png", "season": 2025}, "teams": {"home": {"id": 2945, "name": "Al-Hazm", "logo": "https://media.api-sports.io/football/teams/2945.png"}, "away": {"id": 10513, "name": "NEOM", "logo": "https://media.api-sports.io/football/teams/10513.png"}}, "goals": {"home": 1, "away": 2}, "score": {"halftime": {"home": 0, "away": 0}, "fulltime": {"home": 1, "away": 2}, "extratime": {"home": null, "away": null}, "penalty": {"home": null, "away": null}}}, "1379163": {"fixture": {"id": 1379163, "date": "2026-01-04T15:15:00+00:00", "referee": "Craig Pawson, England", "venue": {"id": 535, "name": "Craven Cottage", "city": "London"}, "status": {"long": "Match Finished", "short": "FT", "elapsed": 90}}, "league": {"id": 39, "name": "Premier League", "country": "England", "logo": "https://media.api-sports.io/football/leagues/39.png", "season": 2025}, "teams": {"home": {"id": 36, "name": "Fulham", "logo": "https://media.api-sports.io/football/teams/36.png"}, "away": {"id": 40, "name": "Liverpool", "logo": "https://media.api-sports.io/football/teams/40.png"}}, "goals": {"home": 2, "away": 2}, "score": {"halftime": {"home": 1, "away": 0}, "fulltime": {"home": 2, "away": 2}, "extratime": {"home": null, "away": null}, "penalty": {"home": null, "away": null}}}, "1390996": {"fixture": {"id": 1390996, "date": "2026-01-04T15:15:00+00:00", "referee": "Alejandro Hernandez, Spain", "venue": {"id": 1456, "name": "Estadio Santiago Bernabéu", "city": "Madrid"}, "status": {"long": "Match Finished", "short": "FT", "elapsed": 90}}, "league": {"id": 140, "name": "La Liga", "country": "Spain", "logo": "https://media.api-sports.io/football/leagues/140.png", "season": 2025}, "teams": {"home": {"id": 541, "name": "Real Madrid", "logo": "https://media.api-sports.io/football/teams/541.png"}, "away": {"id": 543, "name": "Real Betis", "logo": "https://media.api-sports.io/football/teams/543.png"}}, "goals": {"home": 5, "away": 1}, "score": {"halftime": {"home": 1, "away": 0}, "fulltime": {"home": 5, "away": 1}, "extratime": {"home": null, "away": null}, "penalty": {"home": null, "away": null}}}, "1396386": {"fixture": {"id": 1396386, "date": "2026-01-04T15:30:00+00:00", "referee": "Vasilica Iancu, Portugal", "venue": {"id": 1288, "name": "Estádio do Rio Ave Futebol Clube", "city": "Vila do Conde"}, "status": {"long": "Match Finished", "short": "FT", "elapsed": 90}}, "league": {"id": 94, "name": "Primeira Liga", "country": "Portugal", "logo": "https://media.api-sports.io/football/leagues/94.png", "season": 2025}, "teams": {"home": {"id": 226, "name": "Rio Ave", "logo": "https://media.api-sports.io/football/teams/226.png"}, "away": {"id": 4716, "name": "Casa Pia", "logo": "https://media.api-sports.io/football/teams/4716.png"}}, "goals": {"home": 3, "away": 1}, "score": {"halftime": {"home": 0, "away": 0}, "fulltime": {"home": 3, "away": 1}, "extratime": {"home": null, "away": null}, "penalty": {"home": null, "away": null}}}, "1501836": {"fixture": {"id": 1501836, "date": "2026-01-04T16:00:00+00:00", "referee": "Boubou Traore, Mali", "venue": {"id": null, "name": "Complexe Sportif Moulay Abdellah", "city": "Rabat"}, "status": {"long": "Match Finished", "short": "FT", "elapsed": 90}}, "league": {"id": 6, "name": "Africa Cup of Nations", "country": "World", "logo": "https://media.api-sports.io/football/leagues/6.png", "season": 2025}, "teams": {"home": {"id": 31, "name": "Morocco", "logo": "https://media.api-sports.io/football/teams/31.png"}, "away": {"id": 1489, "name": "Tanzania", "logo": "https://media.api-sports.io/football/teams/1489.png"}}, "goals": {"home": 1, "away": 0}, "score": {"halftime": {"home": 0, "away": 0}, "fulltime": {"home": 1, "away": 0}, "extratime": {"home": null, "away": null}, "penalty": {"home": null, "away": null}}}, "1387842": {"fixture": {"id": 1387842, "date": "2026-01-04T16:15:00+00:00", "referee": "Jeremy Stinat, France", "venue": {"id": 641, "name": "Stade Francis-Le Blé", "city": "Brest"}, "status": {"long": "Match Finished", "short": "FT", "elapsed": 90}}, "league": {"id": 61, "name": "Ligue 1", "country": "France", "logo": "https://media.api-sports.io/football/leagues/61.png", "season": 2025}, "teams": {"home": {"id": 106, "name": "Stade Brestois 29", "logo": "https://media.api-sports.io/football/teams/106.png"}, "away": {"id": 108, "name": "Auxerre", "logo": "https://media.api-sports.io/football/teams/108.png"}}, "goals": {"home": 2, "away": 0}, "score": {"halftime": {"home": 1, "away": 0}, "fulltime": {"home": 2, "away": 0}, "extratime": {"home": null, "away": null}, "penalty": {"home": null, "away": null}}}, "1387843": {"fixture": {"id": 1387843, "date": "2026-01-04T16:15:00+00:00", "referee": "Hakim Ben el Salem Hadj, France", "venue": {"id": 652, "name": "Stade Océane", "city": "Le Havre"}, "status": {"long": "Match Finished", "short": "FT", "elapsed": 90}}, "league": {"id": 61, "name": "Ligue 1", "country": "France", "logo": "https://media.api-sports.io/football/leagues/61.png", "season": 2025}, "teams": {"home": {"id": 111, "name": "Le Havre", "logo": "https://media.api-sports.io/football/teams/111.png"}, "away": {"id": 77, "name": "Angers", "logo": "https://media.api-sports.io/football/teams/77.png"}}, "goals": {"home": 2, "away": 1}, "score": {"halftime": {"home": 1, "away": 0}, "fulltime": {"home": 2, "away": 1}, "extratime": {"home": null, "away": null}, "penalty": {"home": null, "away": null}}}, "1387845": {"fixture": {"id": 1387845, "date": "2026-01-04T16:15:00+00:00", "referee": "Guillaume Paradis, France", "venue": {"id": 21430, "name": "Stade du Moustoir", "city": "Lorient"}, "status": {"long": "Match Finished", "short": "FT", "elapsed": 90}}, "league": {"id": 61, "name": "Ligue 1", "country": "France", "logo": "https://media.api-sports.io/football/leagues/61.png", "season": 2025}, "teams": {"home": {"id": 97, "name": "Lorient", "logo": "https://media.api-sports.io/football/teams/97.png"}, "away": {"id": 112, "name": "Metz", "logo": "https://media.api-sports.io/football/teams/112.png"}}, "goals": {"home": 1, "away": 1}, "score": {"halftime": {"home": 0, "away": 1}, "fulltime": {"home": 1, "away": 1}, "extratime": {"home": null, "away": null}, "penalty": {"home": null, "away": null}}}, "1502106": {"fixture": {"id": 1502106, "date": "2026-01-04T16:30:00+00:00", "referee": null, "venue": {"id": null, "name": null, "city": null}, "status": {"long": "Not Started", "short": "NS", "elapsed": null}}, "league": {"id": 667, "name": "Friendlies Clubs", "country": "World", "logo": "https://media.api-sports.io/football/leagues/667.png", "season": 2026}, "teams": {"home": {"id": 27312, "name": "Kurkimaen Kisa", "logo": "https://media.api-sports.io/football/teams/27312.png"}, "away": {"id": 9196, "name": "PK-37", "logo": "https://media.api-sports.io/football/teams/9196.png"}}, "goals": {"home": null, "away": null}, "score": {"halftime": {"home": null, "away": null}, "fulltime": {"home": null, "away": null}, "extratime": {"home": null, "away": null}, "penalty": {"home": null, "away": null}}}, "1378043": {"fixture": {"id": 1378043, "date": "2026-01-04T17:00:00+00:00", "referee": "Antonio Rapuano, Italy", "venue": {"id": 0, "name": "Stadio Marcantonio Bentegodi", "city": "Verona"}, "status": {"long": "Match Finished", "short": "FT", "elapsed": 90}}, "league": {"id": 135, "name": "Serie A", "country": "Italy", "logo": "https://media.api-sports.io/football/leagues/135.png", "season": 2025}, "teams": {"home": {"id": 504, "name": "Verona", "logo": "https://media.api-sports.io/football/teams/504.png"}, "away": {"id": 503, "name": "Torino", "logo": "https://media.api-sports.io/football/teams/503.png"}}, "goals": {"home": 0, "away": 3}, "score": {"halftime": {"home": 0, "away": 1}, "fulltime": {"home": 0, "away": 3}, "extratime": {"home": null, "away": null}, "penalty": {"home": null, "away": null}}}, "1379165": {"fixture": {"id": 1379165, "date": "2026-01-04T17:30:00+00:00", "referee": "Michael Oliver, England", "venue": {"id": 555, "name": "Etihad Stadium", "city": "Manchester"}, "status": {"long": "Second Half", "short": "2H", "elapsed": 76}}, "league": {"id": 39, "name": "Premier League", "country": "England", "logo": "https://media.api-sports.io/football/leagues/39.png", "season": 2025}, "teams": {"home": {"id": 50, "name": "Manchester City", "logo": "https://media.api-sports.io/football/teams/50.png"}, "away": {"id": 49, "name": "Chelsea", "logo": "https://media.api-sports.io/football/teams/49.png"}}, "goals": {"home": 1, "away": 0}, "score": {"halftime": {"home": 1, "away": 0}, "fulltime": {"home": null, "away": null}, "extratime": {"home": null, "away": null}, "penalty": {"home": null, "away": null}}}, "1390989": {"fixture": {"id": 1390989, "date": "2026-01-04T17:30:00+00:00", "referee": "Maria Eugenia Gil, Spain", "venue": {"id": 1470, "name": "Estadio Mendizorrotza", "city": "Vitoria-Gasteiz"}, "status": {"long": "Second Half", "short": "2H", "elapsed": 81}}, "league": {"id": 140, "name": "La Liga", "country": "Spain", "logo": "https://media.api-sports.io/football/leagues/140.png", "season": 2025}, "teams": {"home": {"id": 542, "name": "Alaves", "logo": "https://media.api-sports.io/football/teams/542.png"}, "away": {"id": 718, "name": "Oviedo", "logo": "https://media.api-sports.io/football/teams/718.png"}}, "goals": {"home": 1, "away": 1}, "score": {"halftime": {"home": 0, "away": 0}, "fulltime": {"home": null, "away": null}, "extratime": {"home": null, "away": null}, "penalty": {"home": null, "away": null}}}, "1390993": {"fixture": {"id": 1390993, "date": "2026-01-04T17:30:00+00:00", "referee": "Javier Alberola Rojas, Spain", "venue": {"id": 19940, "name": "Estadi Mallorca Son Moix", "city": "Palma de Mallorca"}, "status": {"long": "Second Half", "short": "2H", "elapsed": 78}}, "league": {"id": 140, "name": "La Liga", "country": "Spain", "logo": "https://media.api-sports.io/football/leagues/140.png", "season": 2025}, "teams": {"home": {"id": 798, "name": "Mallorca", "logo": "https://media.api-sports.io/football/teams/798.png"}, "away": {"id": 547, "name": "Girona", "logo": "https://media.api-sports.io/football/teams/547.png"}}, "goals": {"home": 0, "away": 2}, "score": {"halftime": {"home": 0, "away": 1}, "fulltime": {"home": null, "away": null}, "extratime": {"home": null, "away": null}, "penalty": {"home": null, "away": null}}}, "1436026": {"fixture": {"id": 1436026, "date": "2026-01-04T17:30:00+00:00", "referee": "Eric Lambrechts, Belgium", "venue": {"id": 10516, "name": "Prince Sultan bin Abdul Aziz Stadium", "city": "Abha"}, "status": {"long": "Second Half", "short": "2H", "elapsed": 81}}, "league": {"id": 307, "name": "Pro League", "country": "Saudi-Arabia", "logo": "https://media.api-sports.io/football/leagues/307.png", "season": 2025}, "teams": {"home": {"id": 2956, "name": "Damac", "logo": "https://media.api-sports.io/football/teams/2956.png"}, "away": {"id": 2932, "name": "Al-Hilal Saudi FC", "logo": "https://media.api-sports.io/football/teams/2932.png"}}, "goals": {"home": 0, "away": 2}, "score": {"halftime": {"home": 0, "away": 1}, "fulltime": {"home": null, "away": null}, "extratime": {"home": null, "away": null}, "penalty": {"home": null, "away": null}}}, "1436028": {"fixture": {"id": 1436028, "date": "2026-01-04T17:30:00+00:00", "referee": "Shukri Alhunfush, Saudi Arabia", "venue": {"id": 1370, "name": "Prince Saud bin Jalawi Stadium", "city": "Dammam"}, "status": {"long": "Second Half", "short": "2H", "elapsed": 79}}, "league": {"id": 307, "name": "Pro League", "country": "Saudi-Arabia", "logo": "https://media.api-sports.io/football/leagues/307.png", "season": 2025}, "teams": {"home": {"id": 2933, "name": "Al-Qadisiyah FC", "logo": "https://media.api-sports.io/football/teams/2933.png"}, "away": {"id": 10511, "name": "Al Riyadh", "logo": "https://media.api-sports.io/football/teams/10511.png"}}, "goals": {"home": 3, "away": 0}, "score": {"halftime": {"home": 2, "away": 0}, "fulltime": {"home": null, "away": null}, "extratime": {"home": null, "away": null}, "penalty": {"home": null, "away": null}}}, "1396387": {"fixture": {"id": 1396387, "date": "2026-01-04T18:00:00+00:00", "referee": "Claudio Filipe Ruivo Pereira, Portugal", "venue": {"id": 1289, "name": "Estádio de São Miguel", "city": "Ponta Delgada"}, "status": {"long": "Second Half", "short": "2H", "elapsed": 47}}, "league": {"id": 94, "name": "Primeira Liga", "country": "Portugal", "logo": "https://media.api-sports.io/football/leagues/94.png", "season": 2025}, "teams": {"home": {"id": 227, "name": "Santa Clara", "logo": "https://media.api-sports.io/football/teams/227.png"}, "away": {"id": 212, "name": "FC Porto", "logo": "https://media.api-sports.io/football/teams/212.png"}}, "goals": {"home": 0, "away": 0}, "score": {"halftime": {"home": 0, "away": 0}, "fulltime": {"home": null, "away": null}, "extratime": {"home": null, "away": null}, "penalty": {"home": null, "away": null}}}, "1501837": {"fixture": {"id": 1501837, "date": "2026-01-04T19:00:00+00:00", "referee": "Peter Waweru, Kenya", "venue": {"id": null, "name": "Al-Medina Stadium", "city": "Rabat"}, "status": {"long": "First Half", "short": "1H", "elapsed": 8}}, "league": {"id": 6, "name": "Africa Cup of Nations", "country": "World", "logo": "https://media.api-sports.io/football/leagues/6.png", "season": 2025}, "teams": {"home": {"id": 1531, "name": "South Africa", "logo": "https://media.api-sports.io/football/teams/1531.png"}, "away": {"id": 1530, "name": "Cameroon", "logo": "https://media.api-sports.io/football/teams/1530.png"}}, "goals": {"home": 0, "away": 0}, "score": {"halftime": {"home": 0, "away": 0}, "fulltime": {"home": null, "away": null}, "extratime": {"home": null, "away": null}, "penalty": {"home": null, "away": null}}}, "1378039": {"fixture": {"id": 1378039, "date": "2026-01-04T19:45:00+00:00", "referee": null, "venue": {"id": 907, "name": "Stadio Giuseppe Meazza", "city": "Milan"}, "status": {"long": "Not Started", "short": "NS", "elapsed": null}}, "league": {"id": 135, "name": "Serie A", "country": "Italy", "logo": "https://media.api-sports.io/football/leagues/135.png", "season": 2025}, "teams": {"home": {"id": 505, "name": "Inter", "logo": "https://media.api-sports.io/football/teams/505.png"}, "away": {"id": 500, "name": "Bologna", "logo": "https://media.api-sports.io/football/teams/500.png"}}, "goals": {"home": null, "away": null}, "score": {"halftime": {"home": null, "away": null}, "fulltime": {"home": null, "away": null}, "extratime": {"home": null, "away": null}, "penalty": {"home": null, "away": null}}}, "1387849": {"fixture": {"id": 1387849, "date": "2026-01-04T19:45:00+00:00", "referee": null, "venue": {"id": 671, "name": "Parc des Princes", "city": "Paris"}, "status": {"long": "Not Started", "short": "NS", "elapsed": null}}, "league": {"id": 61, "name": "Ligue 1", "country": "France", "logo": "https://media.api-sports.io/football/leagues/61.png", "season": 2025}, "teams": {"home": {"id": 85, "name": "Paris Saint Germain", "logo": "https://media.api-sports.io/football/teams/85.png"}, "away": {"id": 114, "name": "Paris FC", "logo": "https://media.api-sports.io/football/teams/114.png"}}, "goals": {"home": null, "away": null}, "score": {"halftime": {"home": null, "away": null}, "fulltime": {"home": null, "away": null}, "extratime": {"home": null, "away": null}, "penalty": {"home": null, "away": null}}}, "1390997": {"fixture": {"id": 1390997, "date": "2026-01-04T20:00:00+00:00", "referee": null, "venue": {"id": null, "name": "Reale Arena", "city": "San Sebastian"}, "status": {"long": "Not Started", "short": "NS", "elapsed": null}}, "league": {"id": 140, "name": "La Liga", "country": "Spain", "logo": "https://media.api-sports.io/football/leagues/140.png", "season": 2025}, "teams": {"home": {"id": 548, "name": "Real Sociedad", "logo": "https://media.api-sports.io/football/teams/548.png"}, "away": {"id": 530, "name": "Atletico Madrid", "logo": "https://media.api-sports.io/football/teams/530.png"}}, "goals": {"home": null, "away": null}, "score": {"halftime": {"home": null, "away": null}, "fulltime": {"home": null, "away": null}, "extratime": {"home": null, "away": null}, "penalty": {"home": null, "away": null}}}, "1396382": {"fixture": {"id": 1396382, "date": "2026-01-04T20:30:00+00:00", "referee": null, "venue": {"id": 3572, "name": "FC Alverca Sports Complex", "city": "Alverca do Ribatejo"}, "status": {"long": "Not Started", "short": "NS", "elapsed": null}}, "league": {"id": 94, "name": "Primeira Liga", "country": "Portugal", "logo": "https://media.api-sports.io/football/leagues/94.png", "season": 2025}, "teams": {"home": {"id": 4724, "name": "Alverca", "logo": "https://media.api-sports.io/football/teams/4724.png"}, "away": {"id": 242, "name": "Famalicao", "logo": "https://media.api-sports.io/football/teams/242.png"}}, "goals": {"home": null, "away": null}, "score": {"halftime": {"home": null, "away": null}, "fulltime": {"home": null, "away": null}, "extratime": {"home": null, "away": null}, "penalty": {"home": null, "away": null}}}}