[
  {
    "position": 1,
    "points": 575,
    "wins": 19,
    "name": "Max Verstappen",
    "logo": "https://media.api-sports.io/formula-1/drivers/25.png",
    "teamName": "Red Bull Racing",
    "teamLogo": "https://media.api-sports.io/formula-1/teams/1.png",
    "driver": {
      "name": "Max Verstappen",
      "code": "VER",
      "nationality": null,
      "image": "https://media.api-sports.io/formula-1/drivers/25.png"
    },
    "team": {
      "name": "Red Bull Racing",
      "logo": "https://media.api-sports.io/formula-1/teams/1.png",
      "nationality": null
    }
  },
  {
    "position": 2,
    "points": 285,
    "wins": 2,
    "name": "Sergio Perez",
    "logo": "https://media.api-sports.io/formula-1/drivers/10.png",
    "teamName": "Red Bull Racing",
    "teamLogo": "https://media.api-sports.io/formula-1/teams/1.png",
    "driver": {
      "name": "Sergio Perez",
      "code": "PER",
      "nationality": null,
      "image": "https://media.api-sports.io/formula-1/drivers/10.png"
    },
    "team": {
      "name": "Red Bull Racing",
      "logo": "https://media.api-sports.io/formula-1/teams/1.png",
      "nationality": null
    }
  },
  {
    "position": 3,
    "points": 234,
    "wins": null,
    "name": "Lewis Hamilton",
    "logo": "https://media.api-sports.io/formula-1/drivers/20.png",
    "teamName": "Mercedes-AMG Petronas",
    "teamLogo": "https://media.api-sports.io/formula-1/teams/5.png",
    "driver": {
      "name": "Lewis Hamilton",
      "code": "HAM",
      "nationality": null,
      "image": "https://media.api-sports.io/formula-1/drivers/20.png"
    },
    "team": {
      "name": "Mercedes-AMG Petronas",
      "logo": "https://media.api-sports.io/formula-1/teams/5.png",
      "nationality": null
    }
  },
  {
    "position": 4,
    "points": 206,
    "wins": null,
    "name": "Fernando Alonso",
    "logo": "https://media.api-sports.io/formula-1/drivers/4.png",
    "teamName": "Aston Martin F1 Team",
    "teamLogo": "https://media.api-sports.io/formula-1/teams/17.png",
    "driver": {
      "name": "Fernando Alonso",
      "code": "ALO",
      "nationality": null,
      "image": "https://media.api-sports.io/formula-1/drivers/4.png"
    },
    "team": {
      "name": "Aston Martin F1 Team",
      "logo": "https://media.api-sports.io/formula-1/teams/17.png",
      "nationality": null
    }
  },
  {
    "position": 5,
    "points": 206,
    "wins": null,
    "name": "Charles Leclerc",
    "logo": "https://media.api-sports.io/formula-1/drivers/34.png",
    "teamName": "Scuderia Ferrari",
    "teamLogo": "https://media.api-sports.io/formula-1/teams/3.png",
    "driver": {
      "name": "Charles Leclerc",
      "code": "LEC",
      "nationality": null,
      "image": "https://media.api-sports.io/formula-1/drivers/34.png"
    },
    "team": {
      "name": "Scuderia Ferrari",
      "logo": "https://media.api-sports.io/formula-1/teams/3.png",
      "nationality": null
    }
  },
  {
    "position": 6,
    "points": 205,
    "wins": null,
    "name": "Lando Norris",
    "logo": "https://media.api-sports.io/formula-1/drivers/49.png",
    "teamName": "McLaren Racing",
    "teamLogo": "https://media.api-sports.io/formula-1/teams/2.png",
    "driver": {
      "name": "Lando Norris",
      "code": "NOR",
      "nationality": null,
      "image": "https://media.api-sports.io/formula-1/drivers/49.png"
    },
    "team": {
      "name": "McLaren Racing",
      "logo": "https://media.api-sports.io/formula-1/teams/2.png",
      "nationality": null
    }
  },
  {
    "position": 7,
    "points": 200,
    "wins": 1,
    "name": "Carlos Sainz Jr",
    "logo": "https://media.api-sports.io/formula-1/drivers/24.png",
    "teamName": "Scuderia Ferrari",
    "teamLogo": "https://media.api-sports.io/formula-1/teams/3.png",
    "driver": {
      "name": "Carlos Sainz Jr",
      "code": "SAI",
      "nationality": null,
      "image": "https://media.api-sports.io/formula-1/drivers/24.png"
    },
    "team": {
      "name": "Scuderia Ferrari",
      "logo": "https://media.api-sports.io/formula-1/teams/3.png",
      "nationality": null
    }
  },
  {
    "position": 8,
    "points": 175,
    "wins": null,
    "name": "George Russell",
    "logo": "https://media.api-sports.io/formula-1/drivers/51.png",
    "teamName": "Mercedes-AMG Petronas",
    "teamLogo": "https://media.api-sports.io/formula-1/teams/5.png",
    "driver": {
      "name": "George Russell",
      "code": "RUS",
      "nationality": null,
      "image": "https://media.api-sports.io/formula-1/drivers/51.png"
    },
    "team": {
      "name": "Mercedes-AMG Petronas",
      "logo": "https://media.api-sports.io/formula-1/teams/5.png",
      "nationality": null
    }
  },
  {
    "position": 9,
    "points": 97,
    "wins": null,
    "name": "Oscar Piastri",
    "logo": "https://media.api-sports.io/formula-1/drivers/97.png",
    "teamName": "McLaren Racing",
    "teamLogo": "https://media.api-sports.io/formula-1/teams/2.png",
    "driver": {
      "name": "Oscar Piastri",
      "code": "PIA",
      "nationality": null,
      "image": "https://media.api-sports.io/formula-1/drivers/97.png"
    },
    "team": {
      "name": "McLaren Racing",
      "logo": "https://media.api-sports.io/formula-1/teams/2.png",
      "nationality": null
    }
  },
  {
    "position": 10,
    "points": 74,
    "wins": null,
    "name": "Lance Stroll",
    "logo": "https://media.api-sports.io/formula-1/drivers/31.png",
    "teamName": "Aston Martin F1 Team",
    "teamLogo": "https://media.api-sports.io/formula-1/teams/17.png",
    "driver": {
      "name": "Lance Stroll",
      "code": "STR",
      "nationality": null,
      "image": "https://media.api-sports.io/formula-1/drivers/31.png"
    },
    "team": {
      "name": "Aston Martin F1 Team",
      "logo": "https://media.api-sports.io/formula-1/teams/17.png",
      "nationality": null
    }
  },
  {
    "position": 11,
    "points": 62,
    "wins": null,
    "name": "Pierre Gasly",
    "logo": "https://media.api-sports.io/formula-1/drivers/36.png",
    "teamName": "Alpine F1 Team",
    "teamLogo": "https://media.api-sports.io/formula-1/teams/13.png",
    "driver": {
      "name": "Pierre Gasly",
      "code": "GAS",
      "nationality": null,
      "image": "https://media.api-sports.io/formula-1/drivers/36.png"
    },
    "team": {
      "name": "Alpine F1 Team",
      "logo": "https://media.api-sports.io/formula-1/teams/13.png",
      "nationality": null
    }
  },
  {
    "position": 12,
    "points": 58,
    "wins": null,
    "name": "Esteban Ocon",
    "logo": "https://media.api-sports.io/formula-1/drivers/28.png",
    "teamName": "Alpine F1 Team",
    "teamLogo": "https://media.api-sports.io/formula-1/teams/13.png",
    "driver": {
      "name": "Esteban Ocon",
      "code": "OCO",
      "nationality": null,
      "image": "https://media.api-sports.io/formula-1/drivers/28.png"
    },
    "team": {
      "name": "Alpine F1 Team",
      "logo": "https://media.api-sports.io/formula-1/teams/13.png",
      "nationality": null
    }
  },
  {
    "position": 13,
    "points": 27,
    "wins": null,
    "name": "Alexander Albon",
    "logo": "https://media.api-sports.io/formula-1/drivers/50.png",
    "teamName": "Williams F1 Team",
    "teamLogo": "https://media.api-sports.io/formula-1/teams/12.png",
    "driver": {
      "name": "Alexander Albon",
      "code": "ALB",
      "nationality": null,
      "image": "https://media.api-sports.io/formula-1/drivers/50.png"
    },
    "team": {
      "name": "Williams F1 Team",
      "logo": "https://media.api-sports.io/formula-1/teams/12.png",
      "nationality": null
    }
  },
  {
    "position": 14,
    "points": 17,
    "wins": null,
    "name": "Yuki Tsunoda",
    "logo": "https://media.api-sports.io/formula-1/drivers/82.png",
    "teamName": "Racing Bulls",
    "teamLogo": "https://media.api-sports.io/formula-1/teams/7.png",
    "driver": {
      "name": "Yuki Tsunoda",
      "code": "TSU",
      "nationality": null,
      "image": "https://media.api-sports.io/formula-1/drivers/82.png"
    },
    "team": {
      "name": "Racing Bulls",
      "logo": "https://media.api-sports.io/formula-1/teams/7.png",
      "nationality": null
    }
  },
  {
    "position": 15,
    "points": 10,
    "wins": null,
    "name": "Valtteri Bottas",
    "logo": "https://media.api-sports.io/formula-1/drivers/5.png",
    "teamName": "Stake F1 Team Kick Sauber",
    "teamLogo": "https://media.api-sports.io/formula-1/teams/18.png",
    "driver": {
      "name": "Valtteri Bottas",
      "code": "BOT",
      "nationality": null,
      "image": "https://media.api-sports.io/formula-1/drivers/5.png"
    },
    "team": {
      "name": "Stake F1 Team Kick Sauber",
      "logo": "https://media.api-sports.io/formula-1/teams/18.png",
      "nationality": null
    }
  },
  {
    "position": 16,
    "points": 9,
    "wins": null,
    "name": "Nico Hulkenberg",
    "logo": "https://media.api-sports.io/formula-1/drivers/6.png",
    "teamName": "Haas F1 Team",
    "teamLogo": "https://media.api-sports.io/formula-1/teams/14.png",
    "driver": {
      "name": "Nico Hulkenberg",
      "code": "HUL",
      "nationality": null,
      "image": "https://media.api-sports.io/formula-1/drivers/6.png"
    },
    "team": {
      "name": "Haas F1 Team",
      "logo": "https://media.api-sports.io/formula-1/teams/14.png",
      "nationality": null
    }
  },
  {
    "position": 17,
    "points": 6,
    "wins": null,
    "name": "Daniel Ricciardo",
    "logo": "https://media.api-sports.io/formula-1/drivers/14.png",
    "teamName": "Racing Bulls",
    "teamLogo": "https://media.api-sports.io/formula-1/teams/7.png",
    "driver": {
      "name": "Daniel Ricciardo",
      "code": "RIC",
      "nationality": null,
      "image": "https://media.api-sports.io/formula-1/drivers/14.png"
    },
    "team": {
      "name": "Racing Bulls",
      "logo": "https://media.api-sports.io/formula-1/teams/7.png",
      "nationality": null
    }
  },
  {
    "position": 18,
    "points": 6,
    "wins": null,
    "name": "Guanyu Zhou",
    "logo": "https://media.api-sports.io/formula-1/drivers/83.png",
    "teamName": "Stake F1 Team Kick Sauber",
    "teamLogo": "https://media.api-sports.io/formula-1/teams/18.png",
    "driver": {
      "name": "Guanyu Zhou",
      "code": null,
      "nationality": null,
      "image": "https://media.api-sports.io/formula-1/drivers/83.png"
    },
    "team": {
      "name": "Stake F1 Team Kick Sauber",
      "logo": "https://media.api-sports.io/formula-1/teams/18.png",
      "nationality": null
    }
  },
  {
    "position": 19,
    "points": 3,
    "wins": null,
    "name": "Kevin Magnussen",
    "logo": "https://media.api-sports.io/formula-1/drivers/2.png",
    "teamName": "Haas F1 Team",
    "teamLogo": "https://media.api-sports.io/formula-1/teams/14.png",
    "driver": {
      "name": "Kevin Magnussen",
      "code": "MAG",
      "nationality": null,
      "image": "https://media.api-sports.io/formula-1/drivers/2.png"
    },
    "team": {
      "name": "Haas F1 Team",
      "logo": "https://media.api-sports.io/formula-1/teams/14.png",
      "nationality": null
    }
  },
  {
    "position": 20,
    "points": 2,
    "wins": null,
    "name": "Liam Lawson",
    "logo": "https://media.api-sports.io/formula-1/drivers/89.png",
    "teamName": "Racing Bulls",
    "teamLogo": "https://media.api-sports.io/formula-1/teams/7.png",
    "driver": {
      "name": "Liam Lawson",
      "code": "LAW",
      "nationality": null,
      "image": "https://media.api-sports.io/formula-1/drivers/89.png"
    },
    "team": {
      "name": "Racing Bulls",
      "logo": "https://media.api-sports.io/formula-1/teams/7.png",
      "nationality": null
    }
  },
  {
    "position": 21,
    "points": 1,
    "wins": null,
    "name": "Logan Sargeant",
    "logo": "https://media.api-sports.io/formula-1/drivers/92.png",
    "teamName": "Williams F1 Team",
    "teamLogo": "https://media.api-sports.io/formula-1/teams/12.png",
    "driver": {
      "name": "Logan Sargeant",
      "code": null,
      "nationality": null,
      "image": "https://media.api-sports.io/formula-1/drivers/92.png"
    },
    "team": {
      "name": "Williams F1 Team",
      "logo": "https://media.api-sports.io/formula-1/teams/12.png",
      "nationality": null
    }
  },
  {
    "position": 22,
    "points": null,
    "wins": null,
    "name": "Nyck De Vries",
    "logo": "https://media.api-sports.io/formula-1/drivers/88.png",
    "teamName": "Racing Bulls",
    "teamLogo": "https://media.api-sports.io/formula-1/teams/7.png",
    "driver": {
      "name": "Nyck De Vries",
      "code": null,
      "nationality": null,
      "image": "https://media.api-sports.io/formula-1/drivers/88.png"
    },
    "team": {
      "name": "Racing Bulls",
      "logo": "https://media.api-sports.io/formula-1/teams/7.png",
      "nationality": null
    }
  }
]